{
   "agent": "lluv-websocket (Lua 5.1 / WS)",
   "behavior": "OK",
   "behaviorClose": "OK",
   "case": 347,
   "closedByMe": true,
   "createStats": true,
   "createWirelog": true,
   "description": "Send 1000 compressed messages each of payload size 8192, auto-fragment to 0 octets. Use default permessage-deflate offer.",
   "droppedByMe": false,
   "duration": 5188,
   "expectation": "Receive echo'ed messages (with payload as sent). Timeout case after 480 secs.",
   "expected": {},
   "expectedClose": {
      "closeCode": [
         1000
      ],
      "closedByMe": true,
      "requireClean": true
   },
   "failedByMe": false,
   "httpRequest": "GET / HTTP/1.1\r\nUser-Agent: AutobahnTestSuite/0.7.1-0.10.0\r\nHost: 127.0.0.1:9000\r\nUpgrade: WebSocket\r\nConnection: Upgrade\r\nPragma: no-cache\r\nCache-Control: no-cache\r\nSec-WebSocket-Key: CMt2BM4kPruPWmO65qmjaA==\r\nSec-WebSocket-Extensions: permessage-deflate; client_no_context_takeover; client_max_window_bits\r\nSec-WebSocket-Version: 13\r\n\r\n",
   "httpResponse": "HTTP/1.1 101 Switching Protocols\r\nUpgrade: websocket\r\nConnection: upgrade\r\nSec-WebSocket-Accept: GOXLEmqxVXWWqScmL91+kbm8Z28=\r\nSec-WebSocket-Extensions: permessage-deflate; client_no_context_takeover; client_max_window_bits=15\r\n\r\n",
   "id": "12.3.6",
   "isServer": false,
   "localCloseCode": 1000,
   "localCloseReason": null,
   "received": [],
   "remoteCloseCode": 1000,
   "remoteCloseReason": null,
   "reportCompressionRatio": true,
   "reportTime": true,
   "result": "Ok, received all echo'ed messages in time.",
   "resultClose": "Connection was properly closed",
   "rxFrameStats": {
      "2": 1000,
      "8": 1
   },
   "rxOctetStats": {
      "4": 1,
      "230": 1,
      "2524": 1,
      "2525": 1,
      "2529": 1,
      "2543": 1,
      "2552": 1,
      "2556": 2,
      "2594": 1,
      "2595": 2,
      "2644": 2,
      "2647": 1,
      "2692": 1,
      "2731": 1,
      "2746": 1,
      "2757": 1,
      "2758": 1,
      "2762": 1,
      "2765": 1,
      "2778": 1,
      "2782": 1,
      "2783": 1,
      "2796": 1,
      "2797": 1,
      "2802": 1,
      "2806": 1,
      "2832": 1,
      "2836": 1,
      "2842": 1,
      "2846": 1,
      "2855": 1,
      "2870": 1,
      "2889": 1,
      "2904": 1,
      "2909": 1,
      "2910": 1,
      "2911": 1,
      "2919": 1,
      "2922": 1,
      "2924": 1,
      "2925": 1,
      "2929": 1,
      "2930": 1,
      "2932": 2,
      "2933": 2,
      "2934": 2,
      "2936": 2,
      "2937": 2,
      "2939": 1,
      "2940": 1,
      "2941": 1,
      "2943": 1,
      "2944": 1,
      "2946": 1,
      "2949": 1,
      "2950": 5,
      "2953": 1,
      "2954": 1,
      "2957": 2,
      "2959": 1,
      "2960": 1,
      "2962": 5,
      "2963": 2,
      "2964": 2,
      "2965": 2,
      "2966": 1,
      "2967": 1,
      "2968": 4,
      "2970": 3,
      "2971": 2,
      "2972": 2,
      "2975": 4,
      "2977": 4,
      "2978": 1,
      "2979": 5,
      "2980": 2,
      "2981": 4,
      "2982": 2,
      "2983": 1,
      "2985": 2,
      "2986": 4,
      "2987": 3,
      "2988": 2,
      "2989": 1,
      "2990": 1,
      "2991": 3,
      "2993": 1,
      "2994": 7,
      "2995": 2,
      "2996": 2,
      "2997": 1,
      "2998": 2,
      "2999": 1,
      "3000": 1,
      "3003": 4,
      "3004": 4,
      "3005": 1,
      "3007": 4,
      "3008": 3,
      "3009": 4,
      "3010": 1,
      "3011": 1,
      "3012": 2,
      "3013": 4,
      "3014": 5,
      "3015": 4,
      "3016": 1,
      "3017": 1,
      "3018": 7,
      "3019": 5,
      "3020": 6,
      "3021": 4,
      "3022": 6,
      "3023": 4,
      "3024": 8,
      "3025": 5,
      "3027": 2,
      "3028": 7,
      "3029": 4,
      "3030": 5,
      "3032": 2,
      "3033": 9,
      "3034": 3,
      "3035": 5,
      "3036": 4,
      "3037": 8,
      "3038": 4,
      "3039": 2,
      "3040": 5,
      "3041": 5,
      "3042": 1,
      "3043": 7,
      "3044": 1,
      "3045": 6,
      "3046": 5,
      "3047": 2,
      "3048": 6,
      "3049": 5,
      "3050": 3,
      "3051": 2,
      "3052": 2,
      "3053": 1,
      "3054": 1,
      "3055": 3,
      "3056": 5,
      "3057": 2,
      "3058": 3,
      "3059": 2,
      "3062": 4,
      "3063": 1,
      "3064": 1,
      "3065": 2,
      "3067": 2,
      "3068": 3,
      "3069": 1,
      "3071": 1,
      "3077": 3,
      "3078": 5,
      "3079": 3,
      "3080": 4,
      "3081": 3,
      "3082": 3,
      "3083": 1,
      "3084": 4,
      "3085": 3,
      "3086": 1,
      "3088": 2,
      "3089": 2,
      "3090": 3,
      "3091": 1,
      "3092": 3,
      "3093": 2,
      "3094": 2,
      "3095": 2,
      "3096": 2,
      "3097": 3,
      "3098": 3,
      "3099": 3,
      "3100": 2,
      "3101": 1,
      "3103": 3,
      "3105": 2,
      "3106": 1,
      "3108": 3,
      "3109": 2,
      "3111": 5,
      "3112": 3,
      "3113": 5,
      "3114": 2,
      "3115": 3,
      "3116": 4,
      "3117": 1,
      "3118": 1,
      "3119": 4,
      "3120": 5,
      "3121": 5,
      "3122": 3,
      "3123": 3,
      "3124": 2,
      "3125": 4,
      "3126": 1,
      "3127": 4,
      "3128": 2,
      "3129": 6,
      "3130": 3,
      "3131": 3,
      "3132": 3,
      "3133": 4,
      "3134": 5,
      "3135": 1,
      "3136": 3,
      "3137": 4,
      "3138": 1,
      "3139": 6,
      "3140": 3,
      "3141": 5,
      "3142": 2,
      "3143": 5,
      "3144": 4,
      "3145": 2,
      "3146": 2,
      "3147": 4,
      "3148": 2,
      "3149": 3,
      "3150": 2,
      "3151": 3,
      "3152": 3,
      "3153": 1,
      "3155": 1,
      "3156": 3,
      "3157": 3,
      "3158": 2,
      "3160": 1,
      "3161": 1,
      "3162": 3,
      "3163": 3,
      "3164": 1,
      "3165": 1,
      "3166": 1,
      "3168": 2,
      "3169": 2,
      "3170": 3,
      "3171": 4,
      "3172": 1,
      "3175": 3,
      "3176": 2,
      "3178": 4,
      "3180": 2,
      "3181": 1,
      "3182": 2,
      "3184": 4,
      "3185": 1,
      "3186": 2,
      "3187": 1,
      "3188": 1,
      "3189": 3,
      "3190": 1,
      "3191": 1,
      "3192": 2,
      "3193": 1,
      "3194": 2,
      "3195": 1,
      "3196": 3,
      "3197": 4,
      "3199": 1,
      "3200": 5,
      "3201": 6,
      "3202": 6,
      "3203": 2,
      "3204": 4,
      "3205": 5,
      "3206": 1,
      "3207": 11,
      "3208": 1,
      "3209": 3,
      "3210": 5,
      "3211": 3,
      "3212": 4,
      "3213": 4,
      "3214": 3,
      "3215": 5,
      "3216": 11,
      "3218": 3,
      "3219": 6,
      "3220": 5,
      "3221": 6,
      "3222": 4,
      "3223": 2,
      "3224": 4,
      "3225": 4,
      "3226": 8,
      "3227": 7,
      "3228": 5,
      "3229": 2,
      "3230": 6,
      "3232": 5,
      "3233": 5,
      "3234": 1,
      "3235": 2,
      "3236": 3,
      "3237": 4,
      "3239": 3,
      "3240": 4,
      "3241": 4,
      "3242": 3,
      "3243": 5,
      "3244": 3,
      "3245": 2,
      "3246": 1,
      "3247": 4,
      "3250": 3,
      "3251": 2,
      "3252": 2,
      "3253": 1,
      "3254": 1,
      "3256": 1,
      "3260": 2,
      "3261": 1,
      "3262": 1,
      "3263": 4,
      "3265": 2,
      "3267": 2,
      "3269": 1,
      "3271": 3,
      "3272": 1,
      "3273": 2,
      "3275": 1,
      "3276": 1,
      "3281": 1,
      "3283": 3,
      "3285": 1,
      "3286": 1,
      "3287": 3,
      "3288": 2,
      "3290": 2,
      "3291": 2,
      "3292": 1,
      "3293": 2,
      "3294": 1,
      "3295": 1,
      "3296": 4,
      "3297": 1,
      "3299": 3,
      "3300": 3,
      "3301": 1,
      "3302": 2,
      "3303": 2,
      "3305": 5,
      "3306": 5,
      "3307": 3,
      "3308": 4,
      "3309": 1,
      "3310": 2,
      "3311": 3,
      "3312": 1,
      "3314": 4,
      "3315": 4,
      "3316": 1,
      "3317": 1,
      "3318": 1,
      "3319": 2,
      "3321": 2,
      "3322": 2,
      "3323": 1,
      "3326": 1,
      "3327": 2,
      "3331": 1,
      "3332": 1,
      "3333": 1,
      "3338": 1,
      "3344": 2,
      "3359": 1,
      "3361": 1,
      "3362": 1,
      "3366": 2,
      "3371": 1,
      "3378": 1,
      "3381": 1,
      "3388": 2,
      "3413": 1,
      "3421": 1,
      "3440": 1,
      "3444": 1,
      "3447": 1,
      "3451": 1,
      "3452": 1,
      "3469": 1,
      "3474": 1,
      "3479": 2,
      "3487": 1,
      "3492": 1,
      "3493": 1,
      "3500": 1,
      "3513": 1,
      "3519": 1,
      "3527": 1,
      "3528": 1,
      "3529": 1,
      "3536": 1,
      "3538": 1,
      "3546": 1,
      "3557": 1,
      "3575": 1,
      "3908": 1
   },
   "started": "2016-03-22T19:18:39.546Z",
   "trafficStats": {
      "incomingCompressionRatio": 0.38098828125,
      "incomingOctetsAppLevel": 8192000,
      "incomingOctetsWebSocketLevel": 3121056,
      "incomingOctetsWireLevel": 3125056,
      "incomingWebSocketFrames": 1000,
      "incomingWebSocketMessages": 1000,
      "incomingWebSocketOverhead": 0.0012816175038192202,
      "outgoingCompressionRatio": 0.443822265625,
      "outgoingOctetsAppLevel": 8192000,
      "outgoingOctetsWebSocketLevel": 3635792,
      "outgoingOctetsWireLevel": 3643792,
      "outgoingWebSocketFrames": 1000,
      "outgoingWebSocketMessages": 1000,
      "outgoingWebSocketOverhead": 0.002200345894374596,
      "preopenIncomingOctetsWireLevel": 230,
      "preopenOutgoingOctetsWireLevel": 338
   },
   "txFrameStats": {
      "2": 1000,
      "8": 1
   },
   "txOctetStats": {
      "8": 1,
      "338": 1,
      "2780": 1,
      "2791": 1,
      "2808": 1,
      "2810": 1,
      "2811": 1,
      "2812": 1,
      "2815": 1,
      "2818": 1,
      "2850": 1,
      "2867": 1,
      "2876": 1,
      "2877": 1,
      "2889": 1,
      "2895": 1,
      "2906": 1,
      "2912": 1,
      "2939": 1,
      "2947": 1,
      "3007": 1,
      "3055": 1,
      "3059": 1,
      "3070": 1,
      "3093": 1,
      "3100": 1,
      "3112": 1,
      "3127": 1,
      "3131": 1,
      "3157": 1,
      "3175": 1,
      "3178": 1,
      "3184": 1,
      "3186": 1,
      "3193": 1,
      "3216": 1,
      "3248": 2,
      "3251": 1,
      "3263": 1,
      "3295": 1,
      "3305": 1,
      "3334": 1,
      "3337": 1,
      "3350": 1,
      "3353": 1,
      "3364": 1,
      "3369": 1,
      "3386": 1,
      "3400": 1,
      "3409": 1,
      "3414": 1,
      "3430": 1,
      "3445": 1,
      "3446": 1,
      "3449": 1,
      "3451": 1,
      "3454": 1,
      "3464": 1,
      "3467": 1,
      "3469": 1,
      "3470": 1,
      "3472": 1,
      "3473": 2,
      "3474": 1,
      "3476": 1,
      "3478": 1,
      "3480": 2,
      "3484": 2,
      "3485": 1,
      "3488": 3,
      "3489": 1,
      "3490": 3,
      "3491": 2,
      "3492": 1,
      "3496": 1,
      "3498": 2,
      "3499": 2,
      "3503": 4,
      "3504": 1,
      "3505": 2,
      "3507": 1,
      "3508": 1,
      "3510": 2,
      "3513": 2,
      "3514": 2,
      "3515": 2,
      "3517": 4,
      "3519": 2,
      "3521": 2,
      "3524": 1,
      "3525": 1,
      "3526": 3,
      "3527": 3,
      "3529": 1,
      "3532": 2,
      "3534": 2,
      "3538": 2,
      "3539": 2,
      "3540": 2,
      "3541": 2,
      "3542": 4,
      "3543": 2,
      "3544": 1,
      "3545": 2,
      "3547": 1,
      "3548": 1,
      "3549": 1,
      "3551": 2,
      "3552": 2,
      "3553": 1,
      "3554": 3,
      "3557": 2,
      "3558": 3,
      "3559": 1,
      "3560": 4,
      "3561": 3,
      "3562": 3,
      "3563": 3,
      "3564": 2,
      "3565": 2,
      "3566": 4,
      "3567": 3,
      "3568": 3,
      "3569": 2,
      "3570": 4,
      "3571": 3,
      "3573": 3,
      "3574": 1,
      "3575": 2,
      "3576": 4,
      "3577": 2,
      "3578": 2,
      "3579": 3,
      "3582": 3,
      "3583": 3,
      "3584": 3,
      "3585": 3,
      "3586": 1,
      "3587": 5,
      "3588": 3,
      "3589": 2,
      "3590": 2,
      "3591": 1,
      "3592": 2,
      "3593": 9,
      "3594": 2,
      "3595": 5,
      "3596": 5,
      "3597": 4,
      "3599": 2,
      "3600": 2,
      "3601": 2,
      "3602": 2,
      "3603": 4,
      "3604": 2,
      "3605": 7,
      "3606": 2,
      "3607": 4,
      "3608": 3,
      "3609": 3,
      "3610": 4,
      "3611": 6,
      "3612": 5,
      "3613": 4,
      "3614": 4,
      "3615": 5,
      "3616": 5,
      "3617": 5,
      "3618": 7,
      "3619": 7,
      "3620": 4,
      "3621": 2,
      "3622": 7,
      "3623": 1,
      "3624": 5,
      "3625": 2,
      "3626": 5,
      "3627": 4,
      "3628": 3,
      "3629": 4,
      "3631": 2,
      "3632": 3,
      "3633": 1,
      "3634": 2,
      "3635": 2,
      "3636": 3,
      "3637": 3,
      "3638": 2,
      "3639": 1,
      "3640": 3,
      "3641": 6,
      "3642": 2,
      "3643": 2,
      "3644": 3,
      "3645": 2,
      "3646": 3,
      "3647": 1,
      "3648": 4,
      "3649": 4,
      "3650": 2,
      "3651": 3,
      "3652": 5,
      "3653": 2,
      "3654": 3,
      "3655": 7,
      "3656": 5,
      "3657": 1,
      "3658": 4,
      "3659": 8,
      "3660": 2,
      "3661": 7,
      "3662": 2,
      "3663": 2,
      "3664": 2,
      "3665": 4,
      "3666": 2,
      "3667": 3,
      "3668": 4,
      "3669": 6,
      "3670": 2,
      "3671": 7,
      "3672": 3,
      "3673": 7,
      "3674": 4,
      "3675": 6,
      "3676": 2,
      "3677": 2,
      "3678": 2,
      "3679": 7,
      "3680": 9,
      "3681": 3,
      "3682": 6,
      "3683": 7,
      "3684": 2,
      "3685": 2,
      "3686": 4,
      "3687": 6,
      "3688": 5,
      "3689": 3,
      "3690": 7,
      "3691": 1,
      "3692": 7,
      "3693": 5,
      "3694": 3,
      "3695": 5,
      "3696": 5,
      "3697": 1,
      "3698": 5,
      "3699": 6,
      "3700": 4,
      "3701": 5,
      "3702": 7,
      "3703": 4,
      "3704": 5,
      "3705": 3,
      "3706": 4,
      "3707": 2,
      "3708": 3,
      "3709": 3,
      "3710": 2,
      "3711": 3,
      "3712": 2,
      "3713": 3,
      "3714": 6,
      "3715": 3,
      "3716": 3,
      "3717": 3,
      "3718": 3,
      "3719": 7,
      "3720": 3,
      "3721": 3,
      "3722": 3,
      "3723": 1,
      "3724": 1,
      "3725": 2,
      "3726": 2,
      "3727": 5,
      "3728": 1,
      "3729": 1,
      "3730": 5,
      "3731": 3,
      "3732": 5,
      "3733": 1,
      "3734": 2,
      "3735": 2,
      "3737": 2,
      "3738": 1,
      "3739": 2,
      "3740": 1,
      "3741": 2,
      "3742": 2,
      "3744": 2,
      "3745": 4,
      "3746": 4,
      "3747": 2,
      "3748": 5,
      "3749": 3,
      "3750": 2,
      "3751": 2,
      "3752": 2,
      "3753": 2,
      "3754": 5,
      "3755": 1,
      "3756": 2,
      "3757": 1,
      "3758": 2,
      "3759": 5,
      "3760": 1,
      "3761": 2,
      "3762": 4,
      "3763": 5,
      "3764": 2,
      "3765": 3,
      "3766": 6,
      "3767": 1,
      "3768": 3,
      "3769": 1,
      "3770": 2,
      "3771": 1,
      "3772": 3,
      "3773": 1,
      "3774": 2,
      "3775": 2,
      "3776": 4,
      "3777": 4,
      "3778": 2,
      "3779": 3,
      "3780": 4,
      "3781": 3,
      "3782": 4,
      "3783": 6,
      "3784": 4,
      "3785": 5,
      "3786": 2,
      "3787": 3,
      "3788": 2,
      "3789": 4,
      "3790": 3,
      "3791": 1,
      "3792": 3,
      "3793": 2,
      "3794": 1,
      "3795": 3,
      "3796": 2,
      "3798": 4,
      "3799": 1,
      "3800": 4,
      "3801": 1,
      "3803": 2,
      "3804": 1,
      "3805": 2,
      "3807": 2,
      "3808": 1,
      "3809": 1,
      "3810": 3,
      "3811": 1,
      "3813": 1,
      "3814": 2,
      "3815": 2,
      "3816": 2,
      "3817": 2,
      "3818": 2,
      "3819": 1,
      "3820": 1,
      "3821": 1,
      "3822": 3,
      "3823": 1,
      "3827": 1,
      "3831": 1,
      "3834": 1,
      "3840": 2,
      "3846": 1,
      "3848": 1,
      "3850": 1,
      "3851": 1,
      "3852": 1,
      "3856": 1,
      "3857": 2,
      "3858": 1,
      "3861": 1,
      "3864": 1,
      "3873": 2,
      "3874": 1,
      "3875": 1,
      "3876": 1,
      "3897": 1,
      "3899": 1,
      "3912": 3,
      "3913": 1,
      "3914": 1,
      "3918": 1,
      "3919": 2,
      "3920": 1,
      "3921": 1,
      "3925": 1,
      "3932": 1,
      "3933": 2,
      "3937": 1,
      "3939": 1,
      "3943": 1,
      "3949": 1,
      "3955": 2
   },
   "wasClean": true,
   "wasCloseHandshakeTimeout": false,
   "wasNotCleanReason": null,
   "wasOpenHandshakeTimeout": false,
   "wasServerConnectionDropTimeout": false,
   "wirelog": [
      [
         "TO",
         [
            338,
            "474554202f20485454502f312e310d0a557365722d4167656e743a204175746f6261686e5465737453756974652f302e372e312d302e31302e300d0a486f7374 ..."
         ],
         false
      ],
      [
         "RO",
         [
            230,
            "485454502f312e312031303120537769746368696e672050726f746f636f6c730d0a557067726164653a20776562736f636b65740d0a436f6e6e656374696f6e ..."
         ]
      ],
      [
         "WLM",
         false
      ],
      [
         "TI",
         480
      ],
      [
         "WLM",
         true
      ],
      [
         "TF",
         [
            2,
            "0x03e8"
         ],
         8,
         true,
         0,
         "326cff36",
         null,
         null,
         false
      ],
      [
         "TO",
         [
            8,
            "8882326cff363184"
         ],
         false
      ],
      [
         "RO",
         [
            4,
            "880203e8"
         ]
      ],
      [
         "RF",
         [
            2,
            "0x03e8"
         ],
         8,
         true,
         0,
         false,
         null
      ]
   ]
}